sequdas_client/__init__.py
sequdas_client/sequdas_client.py
sequdas_client/Config/config.ini
sequdas_client/Lib/__init__.py
sequdas_client/Lib/check.py
sequdas_client/Lib/core.py
sequdas_client/Lib/message.py
sequdas_client/Lib/sample_sheet.py
sequdas_client/Lib/status_db.py
sequdas_client/Lib/status_log.py
sequdas_client-1.0.0.dist-info/LICENSE
sequdas_client-1.0.0.dist-info/METADATA
sequdas_client-1.0.0.dist-info/WHEEL
sequdas_client-1.0.0.dist-info/entry_points.txt
sequdas_client-1.0.0.dist-info/top_level.txt
sequdas_client-1.0.0.dist-info/RECORD
